pyrogram/__init__.py
pyrogram/client.py
pyrogram/connection/__init__.py
pyrogram/connection/connection.py
pyrogram/connection/transport/__init__.py
pyrogram/connection/transport/tcp/__init__.py
pyrogram/connection/transport/tcp/tcp.py
pyrogram/connection/transport/tcp/tcp_abridged.py
pyrogram/connection/transport/tcp/tcp_abridged_o.py
pyrogram/connection/transport/tcp/tcp_full.py
pyrogram/connection/transport/tcp/tcp_intermediate.py
pyrogram/connection/transport/tcp/tcp_intermediate_o.py
pyrogram/crypto/__init__.py
pyrogram/crypto/aes.py
pyrogram/crypto/mtproto.py
pyrogram/crypto/prime.py
pyrogram/crypto/rsa.py
pyrogram/dispatcher.py
pyrogram/emoji.py
pyrogram/enums/__init__.py
pyrogram/enums/auto_name.py
pyrogram/enums/chat_action.py
pyrogram/enums/chat_event_action.py
pyrogram/enums/chat_member_status.py
pyrogram/enums/chat_members_filter.py
pyrogram/enums/chat_type.py
pyrogram/enums/message_entity_type.py
pyrogram/enums/message_media_type.py
pyrogram/enums/message_service_type.py
pyrogram/enums/messages_filter.py
pyrogram/enums/next_code_type.py
pyrogram/enums/parse_mode.py
pyrogram/enums/poll_type.py
pyrogram/enums/sent_code_type.py
pyrogram/enums/user_status.py
pyrogram/errors/__init__.py
pyrogram/errors/rpc_error.py
pyrogram/file_id.py
pyrogram/filters.py
pyrogram/handlers/__init__.py
pyrogram/handlers/callback_query_handler.py
pyrogram/handlers/chat_join_request_handler.py
pyrogram/handlers/chat_member_updated_handler.py
pyrogram/handlers/chosen_inline_result_handler.py
pyrogram/handlers/deleted_messages_handler.py
pyrogram/handlers/disconnect_handler.py
pyrogram/handlers/edited_message_handler.py
pyrogram/handlers/handler.py
pyrogram/handlers/inline_query_handler.py
pyrogram/handlers/message_handler.py
pyrogram/handlers/poll_handler.py
pyrogram/handlers/raw_update_handler.py
pyrogram/handlers/user_status_handler.py
pyrogram/methods/__init__.py
pyrogram/methods/advanced/__init__.py
pyrogram/methods/advanced/invoke.py
pyrogram/methods/advanced/resolve_peer.py
pyrolink-3.0.0.dist-info/COPYING
pyrolink-3.0.0.dist-info/COPYING.lesser
pyrolink-3.0.0.dist-info/METADATA
pyrolink-3.0.0.dist-info/NOTICE
pyrolink-3.0.0.dist-info/WHEEL
pyrolink-3.0.0.dist-info/entry_points.txt
pyrolink-3.0.0.dist-info/RECORD
