Metadata-Version: 2.1
Name: pyrolink
Version: 3.0.0
Summary: Elegant, modern and asynchronous Telegram MTProto API framework in Python for users and bots
Home-page: https://github.com/venombolteop
License: LGPLv3
Author: venombolteop
Author-email: venombolteop@gmail.com
Requires-Python: >=3.7,<4.0
Classifier: License :: Other/Proprietary License
Classifier: Programming Language :: Python :: 3
Classifier: Programming Language :: Python :: 3.7
Classifier: Programming Language :: Python :: 3.8
Classifier: Programming Language :: Python :: 3.9
Classifier: Programming Language :: Python :: 3.10
Classifier: Programming Language :: Python :: 3.11
Classifier: Programming Language :: Python :: 3.12
Classifier: Programming Language :: Python :: 3.13
Requires-Dist: docutils (>=0.20,<0.21)
Requires-Dist: pyaes (==1.6.1)
Requires-Dist: pysocks (==1.7.1)
Project-URL: Documentation, https://docs.pyrogram.org
Project-URL: Repository, https://github.com/venombolteop/pyrolink
